pugixml-0.7.0.dist-info/RECORD
pugixml-0.7.0.dist-info/LICENSE
pugixml-0.7.0.dist-info/WHEEL
pugixml-0.7.0.dist-info/top_level.txt
pugixml-0.7.0.dist-info/METADATA
pugixml/pugi.cpython-312-darwin.so
pugixml/__init__.py
