Metadata-Version: 2.2
Name: pugixml
Version: 0.7.0
Summary: Light-weight, simple and fast XML parser with XPath support
Author-email: Tetsuya Miura <miute.dev@gmail.com>
License: MIT License
Project-URL: pugixml, https://pugixml.org/docs/quickstart.html
Project-URL: Repository, https://github.com/miute/pugixml-python
Project-URL: Documentation, https://miute.github.io/pugixml-python/
Project-URL: Changelog, https://miute.github.io/pugixml-python/changelog.html
Keywords: dom,xml,xpath,xml-parser
Classifier: Development Status :: 4 - Beta
Classifier: Intended Audience :: Developers
Classifier: License :: OSI Approved :: MIT License
Classifier: Operating System :: MacOS :: MacOS X
Classifier: Operating System :: Microsoft :: Windows
Classifier: Operating System :: POSIX
Classifier: Programming Language :: C++
Classifier: Programming Language :: Python :: 3 :: Only
Classifier: Programming Language :: Python :: 3.9
Classifier: Programming Language :: Python :: 3.10
Classifier: Programming Language :: Python :: 3.11
Classifier: Programming Language :: Python :: 3.12
Classifier: Programming Language :: Python :: 3.13
Classifier: Topic :: Software Development :: Libraries
Classifier: Topic :: Text Processing :: Markup :: XML
Requires-Python: >=3.9
License-File: LICENSE
